rufus/__init__.py
rufus/client.py
rufus/scraper/__init__.py
rufus/scraper/crawler.py
rufus/scraper/parser.py
rufus_ai-0.1.3.dist-info/LICENSE
rufus_ai-0.1.3.dist-info/METADATA
rufus_ai-0.1.3.dist-info/WHEEL
rufus_ai-0.1.3.dist-info/top_level.txt
rufus_ai-0.1.3.dist-info/RECORD
