Metadata-Version: 2.1
Name: rufus-ai
Version: 0.1.3
Summary: Rufus: Intelligent Web Data Preparation for RAG Agents
Home-page: https://github.com/LabeebZahed03/Chima-rukus
Author: Labeeb Zahed
Author-email: labeebzahed@gmail.com
Classifier: Programming Language :: Python :: 3
Classifier: Operating System :: OS Independent
Classifier: License :: OSI Approved :: MIT License
Requires-Python: >=3.7
License-File: LICENSE
Requires-Dist: beautifulsoup4>=4.9.3
Requires-Dist: requests>=2.25.1
Requires-Dist: spacy>=3.0.0
Requires-Dist: selenium>=4.0.0
Requires-Dist: webdriver-manager>=3.5.0
